helper.py
helperfunc-0.0.1.dist-info/LICENSE.txt
helperfunc-0.0.1.dist-info/METADATA
helperfunc-0.0.1.dist-info/WHEEL
helperfunc-0.0.1.dist-info/top_level.txt
helperfunc-0.0.1.dist-info/RECORD
